abx_plugin_title/__init__.py
abx_plugin_title/extractor.py
abx_plugin_title/extractors.py
abx_plugin_title-2024.10.27.dist-info/METADATA
abx_plugin_title-2024.10.27.dist-info/WHEEL
abx_plugin_title-2024.10.27.dist-info/entry_points.txt
abx_plugin_title-2024.10.27.dist-info/RECORD
