Metadata-Version: 2.4
Name: abx-plugin-title
Version: 2024.10.27
Summary: Title Extractor
Requires-Python: >=3.10
Requires-Dist: abx-plugin-curl>=2024.10.28
Requires-Dist: abx-spec-config>=0.1.0
Requires-Dist: abx>=0.1.0
